endnote_utils/__init__.py
endnote_utils/cli.py
endnote_utils/core.py
endnote_utils/fullscreen.py
endnote_utils/screen.py
endnote_utils-1.0.3.dist-info/METADATA
endnote_utils-1.0.3.dist-info/WHEEL
endnote_utils-1.0.3.dist-info/entry_points.txt
endnote_utils-1.0.3.dist-info/top_level.txt
endnote_utils-1.0.3.dist-info/RECORD
