Metadata-Version: 2.4
Name: endnote-utils
Version: 1.0.3
Summary: Convert EndNote XML to CSV/JSON/XLSX with streaming parse and TXT report.
Author-email: Minh Quach <minhquach8@gmail.com>
License: MIT
Keywords: endnote,xml,csv,bibliography,research
Classifier: Programming Language :: Python :: 3
Classifier: License :: OSI Approved :: MIT License
Classifier: Operating System :: OS Independent
Requires-Python: >=3.8
Requires-Dist: openpyxl>=3.1.0
